pyfactxx/__init__.py
pyfactxx/lib_factxx.cp38-win_amd64.pyd
pyfactxx/coras/__init__.py
pyfactxx/coras/cli.py
pyfactxx/coras/core.py
pyfactxx/coras/debug.py
pyfactxx/coras/parser.py
pyfactxx/coras/query.py
pyfactxx/coras/util.py
pyfactxx-1.8.1.dist-info/COPYING
pyfactxx-1.8.1.dist-info/METADATA
pyfactxx-1.8.1.dist-info/WHEEL
pyfactxx-1.8.1.dist-info/top_level.txt
pyfactxx-1.8.1.dist-info/RECORD
