Metadata-Version: 2.1
Name: pyfactxx
Version: 1.8.1
Summary: Python bindings to FaCT++ reasoner
Home-page: https://github.com/tilde-lab/pyfactxx
Author: Artur Wroblewski
Author-email: wrobell@riseup.net
Maintainer: Ivan Rygaev, Andrey Sobolev
Maintainer-email: ir@tilde.pro
License: GNU GPL 3.0
Platform: UNKNOWN
Classifier: Development Status :: 4 - Beta
Classifier: Intended Audience :: Science/Research
Classifier: Topic :: Scientific/Engineering :: Artificial Intelligence
Classifier: License :: OSI Approved :: GNU General Public License v3 (GPLv3)
Classifier: Programming Language :: C++
Classifier: Programming Language :: Cython
Classifier: Programming Language :: Lisp
Classifier: Programming Language :: Python :: 3
Classifier: Programming Language :: Python :: 3.6
Classifier: Programming Language :: Python :: 3.7
Classifier: Programming Language :: Python :: 3.8
Classifier: Programming Language :: Python :: 3.9
Classifier: Programming Language :: Python :: 3.10
Requires-Python: >=3.7
